sentry_feishu_gsmini/__init__.py
sentry_feishu_gsmini/forms.py
sentry_feishu_gsmini/plugin.py
sentry_feishu_gsmini-1.15.dist-info/LICENSE
sentry_feishu_gsmini-1.15.dist-info/METADATA
sentry_feishu_gsmini-1.15.dist-info/WHEEL
sentry_feishu_gsmini-1.15.dist-info/entry_points.txt
sentry_feishu_gsmini-1.15.dist-info/top_level.txt
sentry_feishu_gsmini-1.15.dist-info/RECORD
