Metadata-Version: 2.1
Name: sentry-feishu-gsmini
Version: 1.15
Summary: A Sentry extension which send errors stats to FeiShu
Home-page: https://github.com/gsmini/sentry-feishu
Author: gsmini
Author-email: gsmini@sina.cn
License: MIT
Keywords: sentry feishu notify
Platform: UNKNOWN
Classifier: Programming Language :: Python :: 3
Classifier: License :: OSI Approved :: MIT License
